dewan_utils/__init__.py
dewan_utils/async_io/__init__.py
dewan_utils/async_io/async_io.py
dewan_utils/async_io/save_df.py
dewan_utils/async_io/save_fig.py
dewan_utils/logs/__init__.py
dewan_utils/tests/__init__.py
dewan_utils/tests/test_asyncio.py
dewan_utils-0.1.3.dist-info/licenses/LICENSE
dewan_utils-0.1.3.dist-info/METADATA
dewan_utils-0.1.3.dist-info/WHEEL
dewan_utils-0.1.3.dist-info/top_level.txt
dewan_utils-0.1.3.dist-info/RECORD
