Metadata-Version: 2.4
Name: dewan-utils
Version: 0.1.3
Summary: Frequently used tools and boilerplate for the Dewan Lab at Florida State University
Author-email: Austin Pauley <pauley@psy.fsu.edu>
License-Expression: MIT
Project-URL: Homepage, https://github.com/olfactorybehaviorlab/dewan-utils
Requires-Python: >=3.12
License-File: LICENSE
Requires-Dist: matplotlib>=3.10.3
Requires-Dist: numpy
Requires-Dist: pandas
Requires-Dist: xlsxwriter
Dynamic: license-file
